{
  "project_info": {
    "project_number": "717990096451",
    "project_id": "ecosens-7c798",
    "storage_bucket": "ecosens-7c798.appspot.com"
  },
  "client": [
    {
      "client_info": {
        "mobilesdk_app_id": "1:717990096451:android:09196ae71cc05a63d9aef6",
        "android_client_info": {
          "package_name": "com.muffin.ecosens"
        }
      },
      "oauth_client": [],
      "api_key": [
        {
          "current_key": "AIzaSyAmfrJeJOjHS_GiS_lbYDU23uZeB-tf0r4"
        }
      ],
      "services": {
        "appinvite_service": {
          "other_platform_oauth_client": []
        }
      }
    }
  ],
  "configuration_version": "1"
}